mom6/__init__.py
mom6/mom6_module/__init__.py
mom6/mom6_module/mom6_detrend.py
mom6/mom6_module/mom6_export.py
mom6/mom6_module/mom6_forecast_tercile.py
mom6/mom6_module/mom6_indexes.py
mom6/mom6_module/mom6_mhw.py
mom6/mom6_module/mom6_read.py
mom6/mom6_module/mom6_regrid.py
mom6/mom6_module/mom6_statistics.py
mom6/mom6_module/mom6_types.py
mom6/mom6_module/mom6_vector_rotate.py
mom6/mom6_module/time_series_processes.py
mom6/mom6_module/util.py
regional_mom-0.10.dist-info/licenses/LICENSE.md
tests/__init__.py
tests/conftest.py
tests/test_mom6_read.py
regional_mom-0.10.dist-info/METADATA
regional_mom-0.10.dist-info/WHEEL
regional_mom-0.10.dist-info/top_level.txt
regional_mom-0.10.dist-info/RECORD
