Metadata-Version: 2.4
Name: regional_mom
Version: 0.10
Summary: Regional MOM6 CEFI preprocessing and data access
Home-page: https://github.com/NOAA-CEFI-Portal/regional_mom6
Author: Chia-Wei Hsu
Author-email: Chia-Wei Hsu <chia-wei.hsu@noaa.gov>
License: BSD 3-Clause
Project-URL: Homepage, https://github.com/NOAA-CEFI-Portal/regional_mom6
Requires-Python: >=3.11
License-File: LICENSE.md
Requires-Dist: xarray
Requires-Dist: netcdf4
Requires-Dist: xesmf
Requires-Dist: dask
Requires-Dist: pydap
Requires-Dist: pytest
Requires-Dist: beautifulsoup4
Requires-Dist: matplotlib
Dynamic: author
Dynamic: home-page
Dynamic: license-file
Dynamic: requires-python
